wanakana/__init__.py
wanakana/constants.py
wanakana/hiragana.py
wanakana/japanese.py
wanakana/kana.py
wanakana/kanji.py
wanakana/katakana.py
wanakana/mixed.py
wanakana/romaji.py
wanakana/utils.py
wanakana-1.0.1.dist-info/METADATA
wanakana-1.0.1.dist-info/RECORD
wanakana-1.0.1.dist-info/WHEEL
wanakana-1.0.1.dist-info/top_level.txt
