Metadata-Version: 2.1
Name: wanakana
Version: 1.0.1
Summary: A library to assist in detecting Japanese text
Home-page: https://github.com/luke-c/WanaKanaPython
Author: Luke Casey
Author-email: lc94dev@gmail.com
License: UNKNOWN
Platform: UNKNOWN
Classifier: Programming Language :: Python :: 3.6
Classifier: License :: OSI Approved :: MIT License
Classifier: Operating System :: OS Independent
Classifier: Natural Language :: Japanese
